MANIFEST.in
requirements.pip
setup.cfg
setup.py
test-requirements.pip
dmake/__init__.py
dmake/build.py
dmake/cli.py
dmake/errors.py
dmake/template_args.py
dmake/utils.py
docker_make.egg-info/PKG-INFO
docker_make.egg-info/SOURCES.txt
docker_make.egg-info/dependency_links.txt
docker_make.egg-info/entry_points.txt
docker_make.egg-info/requires.txt
docker_make.egg-info/top_level.txt