Metadata-Version: 1.0
Name: docker-make
Version: 1.1.6
Summary: build,tag,and push a bunch of related docker images via a single command
Home-page: https://github.com/CtripCloud/docker-make
Author: jizhilong
Author-email: zhilongji@gmail.com
License: Apache
Keywords: docker,image, build
Platform: UNKNOWN
